nerva/__init__.py
nerva/example.py
nerva-0.0.1.dist-info/LICENSE
nerva-0.0.1.dist-info/METADATA
nerva-0.0.1.dist-info/WHEEL
nerva-0.0.1.dist-info/top_level.txt
nerva-0.0.1.dist-info/RECORD
